TxtToImg/__init__.py
txttoimg-0.1.2.dist-info/LICENSE
txttoimg-0.1.2.dist-info/METADATA
txttoimg-0.1.2.dist-info/WHEEL
txttoimg-0.1.2.dist-info/top_level.txt
txttoimg-0.1.2.dist-info/RECORD
