Metadata-Version: 2.2
Name: TxtToImg
Version: 0.1.2
Summary: A Python library to create images with customizable text overlays.
Home-page: https://github.com/nelvinjazieldeveloper/txt2img
Author: Nelvin Jaziel Marquez (Jaziel Developer)
Author-email: nelvinjazieldeveloper@gmail.com
Classifier: Programming Language :: Python :: 3
Classifier: License :: OSI Approved :: MIT License
Classifier: Operating System :: OS Independent
Requires-Python: >=3.6
License-File: LICENSE
Requires-Dist: opencv-python>=4.5.5
Requires-Dist: numpy>=1.21.0
Requires-Dist: requests>=2.26.0
Dynamic: author
Dynamic: author-email
Dynamic: classifier
Dynamic: description
Dynamic: description-content-type
Dynamic: home-page
Dynamic: requires-dist
Dynamic: requires-python
Dynamic: summary
